monday_client/__init__.py
monday_client/__main__.py
monday_client/client.py
monday_client/exceptions.py
monday_client/fragments.py
monday_client/http.py
monday_client/utils.py
cartagon_monday_client-1.0.4.dist-info/METADATA
cartagon_monday_client-1.0.4.dist-info/WHEEL
cartagon_monday_client-1.0.4.dist-info/top_level.txt
cartagon_monday_client-1.0.4.dist-info/RECORD
