Metadata-Version: 2.4
Name: cartagon-monday-client
Version: 1.0.4
Summary: Cliente Python para integraciones con la API GraphQL de Monday.com
Author-email: Miguel Díaz <mpsdiaz@gmail.com>
License: MIT
Project-URL: Homepage, https://github.com/tu-usuario/cartagon-monday-client
Project-URL: Documentation, https://github.com/tu-usuario/cartagon-monday-client#readme
Project-URL: Source, https://github.com/tu-usuario/cartagon-monday-client
Project-URL: Bug Tracker, https://github.com/tu-usuario/cartagon-monday-client/issues
Keywords: monday,monday.com,graphql,api,cliente,integración
Classifier: Development Status :: 4 - Beta
Classifier: Intended Audience :: Developers
Classifier: License :: OSI Approved :: MIT License
Classifier: Programming Language :: Python :: 3
Classifier: Programming Language :: Python :: 3.10
Classifier: Programming Language :: Python :: 3.11
Classifier: Programming Language :: Python :: 3.12
Classifier: Topic :: Software Development :: Libraries
Classifier: Typing :: Typed
Requires-Python: >=3.10
Requires-Dist: requests>=2.25.0
Provides-Extra: dev
Requires-Dist: pytest>=7.0; extra == "dev"
Requires-Dist: responses>=0.18; extra == "dev"
